dcmbench/__init__.py
dcmbench/model_specifications.py
dcmbench/adapters/__init__.py
dcmbench/adapters/biogeme_adapter.py
dcmbench/adapters/biogeme_vot_adapter.py
dcmbench/adapters/enhanced_biogeme_adapter.py
dcmbench/adapters/factory.py
dcmbench/adapters/pytorch_adapter.py
dcmbench/adapters/pytorch_model.py
dcmbench/adapters/sklearn_adapter.py
dcmbench/adapters/sklearn_model.py
dcmbench/adapters/universal_biogeme_adapter.py
dcmbench/adapters/universal_biogeme_adapter_backup.py
dcmbench/datasets/__init__.py
dcmbench/datasets/dataset_loader.py
dcmbench/datasets/metadata.json
dcmbench/datasets/simple_fetcher.py
dcmbench/model_benchmarker/__init__.py
dcmbench/model_benchmarker/benchmarker.py
dcmbench/model_benchmarker/model_interface.py
dcmbench/utils/__init__.py
dcmbench/utils/biogeme_wrapper.py
dcmbench/utils/individual_parameters.py
dcmbench/utils/metrics.py
dcmbench/utils/model_extensions.py
dcmbench/utils/policy_analysis.py
dcmbench/utils/preprocessing.py
dcmbench/utils/sensitivity_analysis.py
dcmbench/utils/vot_analysis.py
dcmbench/utils/vot_systematic.py
dcmbench/utils/vot_visualization.py
dcmbench-0.1.2.dist-info/licenses/LICENSE
dcmbench-0.1.2.dist-info/METADATA
dcmbench-0.1.2.dist-info/WHEEL
dcmbench-0.1.2.dist-info/top_level.txt
dcmbench-0.1.2.dist-info/RECORD
