Metadata-Version: 2.4
Name: dcmbench
Version: 0.1.2
Summary: A comprehensive benchmarking framework for discrete choice models
Home-page: https://github.com/carlosguirado/dcmbench
Author: Carlos Guirado
Author-email: Carlos Guirado <your.email@example.com>
Maintainer-email: Carlos Guirado <your.email@example.com>
License: MIT
Project-URL: Homepage, https://github.com/carlosguirado/dcmbench
Project-URL: Documentation, https://dcmbench.readthedocs.io
Project-URL: Repository, https://github.com/carlosguirado/dcmbench.git
Project-URL: Bug Tracker, https://github.com/carlosguirado/dcmbench/issues
Keywords: discrete choice,benchmarking,transportation,econometrics,machine learning
Classifier: Development Status :: 4 - Beta
Classifier: Intended Audience :: Science/Research
Classifier: Topic :: Scientific/Engineering
Classifier: License :: OSI Approved :: MIT License
Classifier: Programming Language :: Python :: 3
Classifier: Programming Language :: Python :: 3.8
Classifier: Programming Language :: Python :: 3.9
Classifier: Programming Language :: Python :: 3.10
Classifier: Programming Language :: Python :: 3.11
Classifier: Operating System :: OS Independent
Requires-Python: >=3.8
License-File: LICENSE
Requires-Dist: numpy>=1.19.0
Requires-Dist: pandas>=1.2.0
Requires-Dist: scikit-learn>=0.24.0
Requires-Dist: matplotlib>=3.3.0
Requires-Dist: seaborn>=0.11.0
Requires-Dist: biogeme>=3.2.0
Requires-Dist: requests>=2.25.0
Requires-Dist: scipy>=1.6.0
Provides-Extra: dev
Requires-Dist: pytest>=6.0; extra == "dev"
Requires-Dist: pytest-cov>=2.0; extra == "dev"
Requires-Dist: black>=22.0; extra == "dev"
Requires-Dist: flake8>=4.0; extra == "dev"
Requires-Dist: mypy>=0.900; extra == "dev"
Requires-Dist: sphinx>=4.0; extra == "dev"
Requires-Dist: sphinx-rtd-theme>=1.0; extra == "dev"
Provides-Extra: pytorch
Requires-Dist: torch>=1.10.0; extra == "pytorch"
Dynamic: author
Dynamic: home-page
Dynamic: license-file
Dynamic: requires-python
